.hgignore
TODO
distribute_setup.py
setup.py
Sleepy.egg-info/PKG-INFO
Sleepy.egg-info/SOURCES.txt
Sleepy.egg-info/dependency_links.txt
Sleepy.egg-info/entry_points.txt
Sleepy.egg-info/not-zip-safe
Sleepy.egg-info/requires.txt
Sleepy.egg-info/top_level.txt
sleepy/__init__.py
sleepy/atomish.py
sleepy/config.py
sleepy/controllers.py
sleepy/dbxmlish.py
sleepy/exceptions.py
sleepy/facebookish.py
sleepy/feedies.py
sleepy/lonsies.py
sleepy/markdown2.py
sleepy/pasties.py
sleepy/path.py
sleepy/picasaish.py
sleepy/resource.py
sleepy/routesies.py
sleepy/s3ish.py
sleepy/shorties.py
sleepy/tipes.py
sleepy/twitterish.py
sleepy/util.py
sleepy/xspfish.py
sleepy/yamlish.py
sleepy/youtubish.py
sleepy/static/css/jquery.fancybox.css
sleepy/static/css/jquery.ui.base.css
sleepy/static/css/jquery.ui.lightness.css
sleepy/static/css/jquery.ui.tabs.css
sleepy/static/css/jquery.ui.theme.css
sleepy/static/css/timePicker.css
sleepy/static/css/util.css
sleepy/static/css/images/ui-bg_diagonals-thick_18_b81900_40x40.png
sleepy/static/css/images/ui-bg_diagonals-thick_20_666666_40x40.png
sleepy/static/css/images/ui-bg_flat_10_000000_40x100.png
sleepy/static/css/images/ui-bg_glass_100_f6f6f6_1x400.png
sleepy/static/css/images/ui-bg_glass_100_fdf5ce_1x400.png
sleepy/static/css/images/ui-bg_glass_65_ffffff_1x400.png
sleepy/static/css/images/ui-bg_gloss-wave_35_f6a828_500x100.png
sleepy/static/css/images/ui-bg_highlight-soft_100_eeeeee_1x100.png
sleepy/static/css/images/ui-bg_highlight-soft_75_ffe45c_1x100.png
sleepy/static/css/images/ui-icons_222222_256x240.png
sleepy/static/css/images/ui-icons_228ef1_256x240.png
sleepy/static/css/images/ui-icons_ef8c08_256x240.png
sleepy/static/css/images/ui-icons_ffd27a_256x240.png
sleepy/static/css/images/ui-icons_ffffff_256x240.png
sleepy/static/css/sleepy/reset.css
sleepy/static/css/sleepy/tabbed.css
sleepy/static/css/sleepy/util.css
sleepy/static/images/bigrotation2.gif
sleepy/static/images/facebook_icon.png
sleepy/static/images/facebook_logo.jpg
sleepy/static/images/gmail_icon.gif
sleepy/static/images/play.png
sleepy/static/images/youtube_icon.png
sleepy/static/images/fancybox/blank.gif
sleepy/static/images/fancybox/fancy_close.png
